auto_synthetic_data_platform/__init__.py
auto_synthetic_data_platform/categorical_variables_processing.py
auto_synthetic_data_platform/custom_constraints.py
auto_synthetic_data_platform/experiment_logging.py
auto_synthetic_data_platform/missing_variables_processing.py
auto_synthetic_data_platform/numerical_variables_processing.py
auto_synthetic_data_platform/preprocessing.py
auto_synthetic_data_platform/synthetic_data_model_tuning.py
auto_synthetic_data_platform-0.0.1.dist-info/LICENSE
auto_synthetic_data_platform-0.0.1.dist-info/METADATA
auto_synthetic_data_platform-0.0.1.dist-info/WHEEL
auto_synthetic_data_platform-0.0.1.dist-info/top_level.txt
auto_synthetic_data_platform-0.0.1.dist-info/RECORD
