Metadata-Version: 2.1
Name: auto-synthetic-data-platform
Version: 0.0.1
Summary: Google EMEA gTech Ads Data Science Team's solution to create privacy-safe synthetic data out of real data. The solution is a wrapper around the synthcity package (https://github.com/vanderschaarlab/synthcity) simplifying the process of model tuning.
Home-page: https://github.com/google-marketing-solutions/auto_synthetic_data_platform
Author: Google gTech Ads EMEA Privacy Data Science Team
License: Apache Software License 2.0
Keywords: 1pd privacy ai ml marketing
Classifier: Intended Audience :: Developers
Classifier: Intended Audience :: Science/Research
Classifier: License :: OSI Approved :: Apache Software License
Classifier: Topic :: Scientific/Engineering :: Artificial Intelligence
Requires-Python: >=3.10
License-File: LICENSE
Requires-Dist: fastapi ==0.104.1
Requires-Dist: kaleido ==0.2.1
Requires-Dist: python-multipart ==0.0.6
Requires-Dist: uvicorn ==0.24.0
Requires-Dist: typing-extensions ==4.8.0
Requires-Dist: numpy ==1.23.5
Requires-Dist: torch ==1.13.1
Requires-Dist: tsai ==0.3.2
Requires-Dist: wheel ==0.41.2
Requires-Dist: pandas ==1.5.3
Requires-Dist: optuna ==3.3.0
Requires-Dist: ipython ==7.34.0
Requires-Dist: synthcity >=0.2.9
